ethioqen/__init__.py
ethioqen/calendar_conversion.py
ethioqen/exceptions.py
ethioqen/time_conversion.py
ethioqen/unix_time_conversion.py
ethioqen/utils.py
ethioqen-0.2.1.dist-info/LICENSE
ethioqen-0.2.1.dist-info/METADATA
ethioqen-0.2.1.dist-info/WHEEL
ethioqen-0.2.1.dist-info/top_level.txt
ethioqen-0.2.1.dist-info/RECORD
