Metadata-Version: 2.1
Name: ethioqen
Version: 0.2.1
Summary: A package for Ethiopian date and time conversions
Home-page: https://github.com/beabzk/ethioqen
Author: Beabfekad Zikie
Author-email: Beabfekad Zikie <beabzk@proton.me>
License: MIT
Project-URL: Bug Reports, https://github.com/beabzk/ethioqen/issues
Project-URL: Source, https://github.com/beabzk/ethioqen
Classifier: Development Status :: 3 - Alpha
Classifier: Intended Audience :: Developers
Classifier: License :: OSI Approved :: MIT License
Classifier: Operating System :: OS Independent
Classifier: Programming Language :: Python :: 3
Classifier: Programming Language :: Python :: 3.8
Classifier: Programming Language :: Python :: 3.9
Classifier: Programming Language :: Python :: 3.10
Classifier: Programming Language :: Python :: 3.11
Classifier: Topic :: Software Development :: Libraries :: Python Modules
Classifier: Topic :: Software Development :: Localization
Requires-Python: >=3.8
License-File: LICENSE
